hs_config/__init__.py
hs_config/base.py
hs_config-0.1.3.dist-info/METADATA
hs_config-0.1.3.dist-info/WHEEL
hs_config-0.1.3.dist-info/RECORD
